litecounter.py
litecounter-0.2.dist-info/LICENSE
litecounter-0.2.dist-info/METADATA
litecounter-0.2.dist-info/WHEEL
litecounter-0.2.dist-info/top_level.txt
litecounter-0.2.dist-info/RECORD
