Metadata-Version: 2.1
Name: litecounter
Version: 0.2
Summary: Simple counter built on top of SQLite
Home-page: https://github.com/litements/litecounter
Author: Ricardo Ander-Egg Aguilar
Author-email: rsubacc@gmail.com
License: UNKNOWN
Platform: UNKNOWN
Classifier: Operating System :: OS Independent
Requires-Python: >=3.6
